setup.py
funtest/__init__.py
funtest.egg-info/PKG-INFO
funtest.egg-info/SOURCES.txt
funtest.egg-info/dependency_links.txt
funtest.egg-info/not-zip-safe
funtest.egg-info/top_level.txt