Metadata-Version: 1.0
Name: funtest
Version: 0.0.1
Summary: the funny story in the world
Home-page: UNKNOWN
Author: jeterlee
Author-email: 2198750291@qq.com
License: BSD
Platform: UNKNOWN
